{"扩展":["/notes/big-data/2/","/notes/big-data/5/","/notes/big-data/7/","/notes/big-data/8/","/notes/big-data/9/","/notes/blockchain/3/","/notes/game-client-arch/1/","/notes/game-client-arch/3/","/notes/game-client-arch/4/","/notes/linux-basic/1/","/notes/linux-basic/3/","/notes/linux-basic/5/","/notes/linux-basic/9/","/notes/linux-cluster/2/","/notes/linux-cluster/4/","/notes/linux-virtualization/4/","/notes/models/13/","/posts/reinstall-windows/","/posts/scalability/","/posts/scalability2/","/posts/db-arch-opt/","/posts/jwt/","/posts/distributed-transaction/","/posts/microservices/","/posts/ssl-san-sni/","/posts/game-client-architecture/","/academic/AIPrinciple/3/","/academic/AlgorithmDesignAndAnalyze/6/","/academic/ComputerNetwork/5/","/academic/ComputerOrganizationPrinciple/2/","/academic/ComputerOrganizationPrinciple/3/","/academic/ComputerOrganizationPrinciple/4/","/academic/ComputerOrganizationPrinciple/6/","/academic/LinuxProgrammingEnvironment/2/","/academic/NaturalLanguageProcessing/2/","/academic/PrinciplesOfCommunications/4/","/academic/VHDL/vhdl/"],"扩展名":["/notes/big-data/2/","/notes/blockchain/3/","/notes/linux-basic/3/","/notes/linux-basic/9/"],"扩大":["/notes/big-data/8/","/notes/gre/vocabulary/7/","/notes/models/20/","/notes/models/9/","/academic/AIPrinciple/2/","/academic/ComputerOrganizationPrinciple/4/"],"扩展性":["/notes/big-data/9/","/notes/game-client-arch/1/","/posts/scalability/","/posts/scalability2/","/posts/jwt/","/posts/ssl-san-sni/","/posts/game-client-architecture/"],"扩散":["/notes/gre/vocabulary/4/","/academic/ComputerNetwork/5/"],"扩容":["/notes/linux-basic/5/","/notes/linux-cluster/2/","/notes/linux-network/6/","/posts/reinstall-windows/"],"扩缩容":["/notes/linux-virtualization/4/"],"扩缩":["/notes/linux-virtualization/4/"],"扩张":["/notes/models/8/"],"扩充":["/academic/ComputerGraphics/2/","/academic/ComputerNetwork/7/","/academic/ComputerOrganizationPrinciple/3/","/academic/FundamentalsOfCompiling/1/","/academic/MicrocomputerPrincipleAndInterfaceTechnology/6/","/academic/OperatingSystem/8/"],"扩展卡":["/academic/ComputerOrganizationPrinciple/6/"]}