{"现在":["/notes/blockchain/1/","/notes/financial-economics/1/","/notes/financial-economics/3/","/notes/linux-basic/1/","/notes/linux-basic/3/","/notes/linux-basic/5/","/notes/linux-basic/7/","/notes/linux-cluster/3/","/notes/models/10/","/notes/models/14/","/notes/models/1/","/notes/models/21/","/notes/models/9/","/posts/reinstall-windows/","/posts/access-pt-via-ipv6/","/posts/syncing-in-online-games/","/posts/quantum-computing/","/posts/launch-app-with-hot-key/","/academic/AIPrinciple/1/","/academic/ComputerNetwork/5/","/academic/ComputerOrganizationPrinciple/1/","/academic/ComputerOrganizationPrinciple/4/","/academic/ComputerOrganizationPrinciple/8/","/academic/FormalLanguageAndAutomata/3/","/academic/LinuxProgrammingEnvironment/1/","/academic/LinuxProgrammingEnvironment/3/"],"现象":["/notes/financial-economics/1/","/notes/models/16/","/notes/models/22/","/notes/models/4/","/notes/models/9/","/posts/linux-getopt/","/posts/open-gl-transform-order/","/posts/scalability2/","/academic/ComputerOrganizationPrinciple/5/","/academic/LinuxProgrammingEnvironment/1/","/academic/LinuxProgrammingEnvironment/2/","/academic/OperatingSystem/6/","/academic/PrinciplesOfCommunications/6/","/academic/PrinciplesOfCommunications/7/"],"现货":["/notes/financial-economics/2/"],"现值":["/notes/financial-economics/3/","/notes/models/9/"],"现金":["/notes/financial-economics/3/","/notes/models/20/","/notes/product-manager/4/"],"现金流":["/notes/financial-economics/3/","/notes/models/20/","/notes/product-manager/4/"],"现价":["/notes/financial-economics/3/"],"现状":["/notes/models/10/","/notes/models/4/","/notes/product-manager/1/"],"现代":["/notes/models/14/","/notes/models/15/","/notes/models/18/","/notes/models/19/","/notes/models/23/","/notes/models/3/","/notes/models/5/","/notes/product-manager/3/","/notes/product-manager/4/","/academic/LinuxProgrammingEnvironment/3/"],"现代人":["/notes/models/15/","/notes/models/23/","/notes/models/3/"],"现实":["/notes/models/16/","/notes/models/18/","/notes/models/21/","/notes/models/8/","/notes/product-manager/5/","/posts/ble-raspi-wifi-manager/","/academic/ComputerGraphics/1/"],"现实主义":["/notes/models/18/"],"现金流量":["/notes/models/20/"],"现实生活":["/notes/models/8/"],"现有":["/notes/product-manager/1/","/academic/AIPrinciple/1/","/academic/AlgorithmDesignAndAnalyze/3/"],"现代化":["/notes/product-manager/3/"],"现阶段":["/notes/product-manager/4/","/notes/product-manager/6/"],"现场":["/notes/product-manager/5/","/notes/product-manager/6/","/academic/ComputerOrganizationPrinciple/8/","/academic/MicrocomputerPrincipleAndInterfaceTechnology/6/"],"现成":["/posts/scalability/","/posts/scalability2/"],"现":["/academic/NaturalLanguageProcessing/2/"],"现今":["/academic/Thesis/research-on-remote-data-integrity-auditing-with-bidirectional-verification-in-cloud/"]}