{"观看":["/notes/big-data/1/","/notes/big-data/2/","/notes/big-data/3/","/notes/big-data/4/","/notes/big-data/5/","/notes/big-data/6/","/notes/big-data/7/","/notes/big-data/8/","/notes/big-data/9/","/notes/blockchain/1/","/notes/blockchain/2/","/notes/blockchain/3/","/notes/linux-basic/1/","/notes/linux-basic/2/","/notes/linux-basic/3/","/notes/linux-basic/4/","/notes/linux-basic/5/","/notes/linux-basic/6/","/notes/linux-basic/7/","/notes/linux-basic/8/","/notes/linux-basic/9/","/notes/linux-cluster/1/","/notes/linux-cluster/2/","/notes/linux-cluster/3/","/notes/linux-cluster/4/","/notes/linux-network/1/","/notes/linux-network/2/","/notes/linux-network/3/","/notes/linux-network/4/","/notes/linux-network/5/","/notes/linux-network/6/","/notes/linux-network/7/","/notes/linux-network/8/","/notes/linux-virtualization/1/","/notes/linux-virtualization/2/","/notes/linux-virtualization/3/","/notes/linux-virtualization/4/","/notes/linux-virtualization/5/","/notes/linux-virtualization/6/","/notes/product-manager/1/","/notes/product-manager/2/","/notes/product-manager/3/","/notes/product-manager/4/","/notes/product-manager/5/","/notes/product-manager/6/","/notes/security/10/","/notes/security/1/","/notes/security/2/","/notes/security/3/","/notes/security/4/","/notes/security/5/","/notes/security/6/","/notes/security/7/","/notes/security/8/","/notes/security/9/","/notes/software-test/1/","/posts/scalability/","/posts/db-arch-opt/","/posts/microservices/","/posts/swagger-getting-started/","/posts/embedded-system-getting-started/"],"观察":["/notes/big-data/4/","/notes/models/5/","/notes/models/7/","/notes/product-manager/1/","/notes/product-manager/3/","/notes/product-manager/5/","/notes/product-manager/6/","/posts/open-gl-transform-order/","/academic/ComputerGraphics/10/","/academic/ComputerGraphics/4/","/academic/ComputerGraphics/8/"],"观察者":["/notes/big-data/4/","/academic/ComputerGraphics/8/"],"观察员":["/notes/product-manager/5/"],"观点":["/academic/AIPrinciple/1/"],"观察点":["/academic/ComputerGraphics/10/","/academic/ComputerGraphics/8/"],"观测":["/academic/NaturalLanguageProcessing/5/"]}